<annotation>
	<folder>203~</folder>
	<filename>93.jpg</filename>
	<path>C:\Users\User\Desktop\分配\203~\93.jpg</path>
	<source>
		<database>Unknown</database>
	</source>
	<size>
		<width>226</width>
		<height>226</height>
		<depth>1</depth>
	</size>
	<segmented>0</segmented>
	<object>
		<name>person</name>
		<pose>Unspecified</pose>
		<truncated>0</truncated>
		<difficult>0</difficult>
		<bndbox>
			<xmin>12</xmin>
			<ymin>35</ymin>
			<xmax>36</xmax>
			<ymax>93</ymax>
		</bndbox>
	</object>
	<object>
		<name>person</name>
		<pose>Unspecified</pose>
		<truncated>1</truncated>
		<difficult>0</difficult>
		<bndbox>
			<xmin>216</xmin>
			<ymin>104</ymin>
			<xmax>226</xmax>
			<ymax>196</ymax>
		</bndbox>
	</object>
	<object>
		<name>person</name>
		<pose>Unspecified</pose>
		<truncated>0</truncated>
		<difficult>0</difficult>
		<bndbox>
			<xmin>4</xmin>
			<ymin>16</ymin>
			<xmax>18</xmax>
			<ymax>70</ymax>
		</bndbox>
	</object>
</annotation>
