<annotation>
	<folder>203~</folder>
	<filename>167.jpg</filename>
	<path>C:\Users\User\Desktop\分配\203~\167.jpg</path>
	<source>
		<database>Unknown</database>
	</source>
	<size>
		<width>226</width>
		<height>226</height>
		<depth>1</depth>
	</size>
	<segmented>0</segmented>
	<object>
		<name>person</name>
		<pose>Unspecified</pose>
		<truncated>0</truncated>
		<difficult>0</difficult>
		<bndbox>
			<xmin>63</xmin>
			<ymin>58</ymin>
			<xmax>96</xmax>
			<ymax>126</ymax>
		</bndbox>
	</object>
</annotation>
