<annotation>
	<folder>2</folder>
	<filename>15.jpg</filename>
	<path>C:\Users\user\Downloads\給學弟妹的東西\給學弟妹的東西\PETS2009_train\2\15.jpg</path>
	<source>
		<database>Unknown</database>
	</source>
	<size>
		<width>226</width>
		<height>226</height>
		<depth>1</depth>
	</size>
	<segmented>0</segmented>
	<object>
		<name>person</name>
		<pose>Unspecified</pose>
		<truncated>0</truncated>
		<difficult>0</difficult>
		<bndbox>
			<xmin>122</xmin>
			<ymin>101</ymin>
			<xmax>150</xmax>
			<ymax>198</ymax>
		</bndbox>
	</object>
	<object>
		<name>person</name>
		<pose>Unspecified</pose>
		<truncated>0</truncated>
		<difficult>0</difficult>
		<bndbox>
			<xmin>58</xmin>
			<ymin>62</ymin>
			<xmax>79</xmax>
			<ymax>140</ymax>
		</bndbox>
	</object>
	<object>
		<name>person</name>
		<pose>Unspecified</pose>
		<truncated>0</truncated>
		<difficult>0</difficult>
		<bndbox>
			<xmin>77</xmin>
			<ymin>55</ymin>
			<xmax>108</xmax>
			<ymax>128</ymax>
		</bndbox>
	</object>
	<object>
		<name>person</name>
		<pose>Unspecified</pose>
		<truncated>0</truncated>
		<difficult>0</difficult>
		<bndbox>
			<xmin>146</xmin>
			<ymin>8</ymin>
			<xmax>164</xmax>
			<ymax>63</ymax>
		</bndbox>
	</object>
	<object>
		<name>person</name>
		<pose>Unspecified</pose>
		<truncated>0</truncated>
		<difficult>0</difficult>
		<bndbox>
			<xmin>3</xmin>
			<ymin>5</ymin>
			<xmax>17</xmax>
			<ymax>60</ymax>
		</bndbox>
	</object>
	<object>
		<name>person</name>
		<pose>Unspecified</pose>
		<truncated>1</truncated>
		<difficult>0</difficult>
		<bndbox>
			<xmin>95</xmin>
			<ymin>1</ymin>
			<xmax>113</xmax>
			<ymax>47</ymax>
		</bndbox>
	</object>
	<object>
		<name>person</name>
		<pose>Unspecified</pose>
		<truncated>0</truncated>
		<difficult>0</difficult>
		<bndbox>
			<xmin>31</xmin>
			<ymin>15</ymin>
			<xmax>55</xmax>
			<ymax>72</ymax>
		</bndbox>
	</object>
	<object>
		<name>person</name>
		<pose>Unspecified</pose>
		<truncated>0</truncated>
		<difficult>0</difficult>
		<bndbox>
			<xmin>35</xmin>
			<ymin>4</ymin>
			<xmax>47</xmax>
			<ymax>19</ymax>
		</bndbox>
	</object>
	<object>
		<name>person</name>
		<pose>Unspecified</pose>
		<truncated>0</truncated>
		<difficult>0</difficult>
		<bndbox>
			<xmin>84</xmin>
			<ymin>30</ymin>
			<xmax>103</xmax>
			<ymax>58</ymax>
		</bndbox>
	</object>
</annotation>
