<annotation>
	<folder>2</folder>
	<filename>128.jpg</filename>
	<path>C:\Users\user\Downloads\給學弟妹的東西\給學弟妹的東西\PETS2009_train\2\128.jpg</path>
	<source>
		<database>Unknown</database>
	</source>
	<size>
		<width>226</width>
		<height>226</height>
		<depth>1</depth>
	</size>
	<segmented>0</segmented>
	<object>
		<name>person</name>
		<pose>Unspecified</pose>
		<truncated>0</truncated>
		<difficult>0</difficult>
		<bndbox>
			<xmin>13</xmin>
			<ymin>41</ymin>
			<xmax>49</xmax>
			<ymax>128</ymax>
		</bndbox>
	</object>
	<object>
		<name>person</name>
		<pose>Unspecified</pose>
		<truncated>0</truncated>
		<difficult>0</difficult>
		<bndbox>
			<xmin>146</xmin>
			<ymin>111</ymin>
			<xmax>178</xmax>
			<ymax>209</ymax>
		</bndbox>
	</object>
	<object>
		<name>person</name>
		<pose>Unspecified</pose>
		<truncated>1</truncated>
		<difficult>0</difficult>
		<bndbox>
			<xmin>110</xmin>
			<ymin>150</ymin>
			<xmax>137</xmax>
			<ymax>226</ymax>
		</bndbox>
	</object>
	<object>
		<name>person</name>
		<pose>Unspecified</pose>
		<truncated>0</truncated>
		<difficult>0</difficult>
		<bndbox>
			<xmin>35</xmin>
			<ymin>104</ymin>
			<xmax>73</xmax>
			<ymax>208</ymax>
		</bndbox>
	</object>
	<object>
		<name>person</name>
		<pose>Unspecified</pose>
		<truncated>0</truncated>
		<difficult>0</difficult>
		<bndbox>
			<xmin>183</xmin>
			<ymin>41</ymin>
			<xmax>206</xmax>
			<ymax>110</ymax>
		</bndbox>
	</object>
	<object>
		<name>person</name>
		<pose>Unspecified</pose>
		<truncated>0</truncated>
		<difficult>0</difficult>
		<bndbox>
			<xmin>173</xmin>
			<ymin>28</ymin>
			<xmax>190</xmax>
			<ymax>100</ymax>
		</bndbox>
	</object>
	<object>
		<name>person</name>
		<pose>Unspecified</pose>
		<truncated>1</truncated>
		<difficult>0</difficult>
		<bndbox>
			<xmin>214</xmin>
			<ymin>36</ymin>
			<xmax>226</xmax>
			<ymax>110</ymax>
		</bndbox>
	</object>
</annotation>
